obj2gltf.py
obj2gltf-0.1.3.dist-info/METADATA
obj2gltf-0.1.3.dist-info/WHEEL
obj2gltf-0.1.3.dist-info/RECORD
